packages/__init__.py
packages/encryption.py
packages/data/__init__.py
packages/data/mysql.py
packages/data/sqlite.py
data_handles-0.1.2.dist-info/LICENSE
data_handles-0.1.2.dist-info/METADATA
data_handles-0.1.2.dist-info/WHEEL
data_handles-0.1.2.dist-info/top_level.txt
data_handles-0.1.2.dist-info/RECORD
