Metadata-Version: 2.2
Name: data_handles
Version: 0.1.2
Summary: A simple data handling and encryption package.
Home-page: https://github.com/Janish-1/data_handles
Author: Janish Pancholi
Author-email: janish.pancholi11@gmail.com
Classifier: Programming Language :: Python :: 3
Classifier: License :: OSI Approved :: GNU General Public License v3 (GPLv3)
Classifier: Operating System :: OS Independent
Requires-Python: >=3.6
License-File: LICENSE
Dynamic: author
Dynamic: author-email
Dynamic: classifier
Dynamic: description
Dynamic: description-content-type
Dynamic: home-page
Dynamic: requires-python
Dynamic: summary
